django_appointment_scheduler/__init__.py
django_appointment_scheduler/admin.py
django_appointment_scheduler/models.py
django_appointment_scheduler/serializers.py
django_appointment_scheduler/urls.py
django_appointment_scheduler/views.py
django_appointment_scheduler-0.1.6.dist-info/licenses/LICENSE
django_appointment_scheduler-0.1.6.dist-info/METADATA
django_appointment_scheduler-0.1.6.dist-info/WHEEL
django_appointment_scheduler-0.1.6.dist-info/top_level.txt
django_appointment_scheduler-0.1.6.dist-info/RECORD
